agentvisa/__init__.py
agentvisa/client.py
agentvisa/delegations.py
agentvisa/models.py
agentvisa/py.typed
agentvisa-0.2.0.dist-info/METADATA
agentvisa-0.2.0.dist-info/WHEEL
agentvisa-0.2.0.dist-info/licenses/LICENSE
agentvisa-0.2.0.dist-info/RECORD
