Metadata-Version: 2.4
Name: agentvisa
Version: 0.2.0
Summary: The official Python SDK for the AgentVisa API.
Project-URL: Homepage, https://agentvisa.dev
Project-URL: Documentation, https://docs.agentvisa.dev
Project-URL: Repository, https://github.com/AgentVisa/agentvisa-python
Project-URL: Bug Tracker, https://github.com/AgentVisa/agentvisa-python/issues
Author-email: Chris Clapham <chris@agentvisa.dev>
License: MIT
License-File: LICENSE
Keywords: agent,agentvisa,api,delegation,sdk
Classifier: Development Status :: 3 - Alpha
Classifier: Intended Audience :: Developers
Classifier: License :: OSI Approved :: MIT License
Classifier: Programming Language :: Python :: 3
Classifier: Programming Language :: Python :: 3.8
Classifier: Programming Language :: Python :: 3.9
Classifier: Programming Language :: Python :: 3.10
Classifier: Programming Language :: Python :: 3.11
Classifier: Programming Language :: Python :: 3.12
Classifier: Programming Language :: Python :: 3.13
Classifier: Topic :: Software Development :: Libraries :: Python Modules
Requires-Python: >=3.13
Requires-Dist: pydantic>=2.5
Requires-Dist: requests>=2.25.0
Provides-Extra: dev
Requires-Dist: mypy>=1.0.0; extra == 'dev'
Requires-Dist: pytest-cov>=4.0.0; extra == 'dev'
Requires-Dist: pytest-mock>=3.10.0; extra == 'dev'
Requires-Dist: pytest>=7.0.0; extra == 'dev'
Requires-Dist: responses>=0.23.0; extra == 'dev'
Requires-Dist: ruff>=0.12.4; extra == 'dev'
Requires-Dist: types-requests>=2.25.0; extra == 'dev'
